<?xml version="1.0" encoding="utf-8" ?>
<dwsync>
<file name="signika-bold-webfont.eot" server="ftp.wedodo.com//public_html/" local="130040688840000000" remote="130077468000000000" Dst="1" />
<file name="signika-bold-webfont.woff" server="ftp.wedodo.com//public_html/" local="130040688840000000" remote="130077468000000000" Dst="1" />
<file name="signika-light-webfont.eot" server="ftp.wedodo.com//public_html/" local="130040724960000000" remote="130077468600000000" Dst="1" />
<file name="signika-bold-webfont.ttf" server="ftp.wedodo.com//public_html/" local="130040688840000000" remote="130077468600000000" Dst="1" />
<file name="signika-light-webfont.svg" server="ftp.wedodo.com//public_html/" local="130040724960000000" remote="130077468600000000" Dst="1" />
<file name="signika-bold-webfont.svg" server="ftp.wedodo.com//public_html/" local="130040688840000000" remote="130077468600000000" Dst="1" />
<file name="signika-light-webfont.ttf" server="ftp.wedodo.com//public_html/" local="130040724960000000" remote="130077468600000000" Dst="1" />
<file name="signika-light-webfont.woff" server="ftp.wedodo.com//public_html/" local="130040724960000000" remote="130077468600000000" Dst="1" />
<file name="signika-bold-webfont.eot" server="ftp.businessndeals.com/public_html/shantingo/" local="130040688840000000" remote="130079453400000000" Dst="1" />
<file name="signika-bold-webfont.woff" server="ftp.businessndeals.com/public_html/shantingo/" local="130040688840000000" remote="130079453400000000" Dst="1" />
<file name="signika-bold-webfont.ttf" server="ftp.businessndeals.com/public_html/shantingo/" local="130040688840000000" remote="130079453400000000" Dst="1" />
<file name="signika-bold-webfont.svg" server="ftp.businessndeals.com/public_html/shantingo/" local="130040688840000000" remote="130079453400000000" Dst="1" />
<file name="signika-light-webfont.eot" server="ftp.businessndeals.com/public_html/shantingo/" local="130040724960000000" remote="130079453400000000" Dst="1" />
<file name="signika-light-webfont.woff" server="ftp.businessndeals.com/public_html/shantingo/" local="130040724960000000" remote="130079453400000000" Dst="1" />
<file name="signika-light-webfont.svg" server="ftp.businessndeals.com/public_html/shantingo/" local="130040724960000000" remote="130079453400000000" Dst="1" />
<file name="signika-light-webfont.ttf" server="ftp.businessndeals.com/public_html/shantingo/" local="130040724960000000" remote="130079453400000000" Dst="1" />
<file name="index.php" server="ftp.businessndeals.com/public_html/shantingo/" local="130028032644668217" remote="130079491800000000" Dst="1" />
<file name="index.php" server="ftp.rajeshivaji.com" local="130028194644668217" remote="130264203600000000" Dst="2" />
<file name="signika-bold-webfont.eot" server="ftp.rajeshivaji.com" local="130040850840000000" remote="130264203600000000" Dst="2" />
<file name="signika-bold-webfont.svg" server="ftp.rajeshivaji.com" local="130040850840000000" remote="130264203600000000" Dst="2" />
<file name="signika-bold-webfont.ttf" server="ftp.rajeshivaji.com" local="130040850840000000" remote="130264203600000000" Dst="2" />
<file name="signika-bold-webfont.woff" server="ftp.rajeshivaji.com" local="130040850840000000" remote="130264203600000000" Dst="2" />
<file name="signika-light-webfont.eot" server="ftp.rajeshivaji.com" local="130040886960000000" remote="130264203600000000" Dst="2" />
<file name="signika-light-webfont.svg" server="ftp.rajeshivaji.com" local="130040886960000000" remote="130264203600000000" Dst="2" />
<file name="signika-light-webfont.ttf" server="ftp.rajeshivaji.com" local="130040886960000000" remote="130264203600000000" Dst="2" />
<file name="signika-light-webfont.woff" server="ftp.rajeshivaji.com" local="130040886960000000" remote="130264203600000000" Dst="2" />
</dwsync>